werkflow/__init__.py
werkflow/cli/__init__.py
werkflow/cli/base.py
werkflow/cli/run.py
werkflow/cli/exceptions/__init__.py
werkflow/cli/exceptions/empty_workflow_file_error.py
werkflow/cli/exceptions/multiple_workflows_violation_error.py
werkflow/cli/import_tools/__init__.py
werkflow/cli/import_tools/workflow.py
werkflow/cli/signals/__init__.py
werkflow/cli/signals/abort.py
werkflow/connections/__init__.py
werkflow/connections/encryption/__init__.py
werkflow/connections/encryption/aes_gcm.py
werkflow/connections/env/__init__.py
werkflow/connections/env/time_parser.py
werkflow/env/__init__.py
werkflow/env/env.py
werkflow/env/load_env.py
werkflow/env/time_parser.py
werkflow/graph/__init__.py
werkflow/graph/graph.py
werkflow/graph/workflow.py
werkflow/graph/workflow_group.py
werkflow/graph/exceptions/__init__.py
werkflow/graph/exceptions/step_timeout_error.py
werkflow/hooks/__init__.py
werkflow/hooks/types/__init__.py
werkflow/hooks/types/base/__init__.py
werkflow/hooks/types/base/base_hook.py
werkflow/hooks/types/base/hook_types.py
werkflow/hooks/types/base/registrar.py
werkflow/hooks/types/requires/__init__.py
werkflow/hooks/types/requires/decorator.py
werkflow/hooks/types/requires/validator.py
werkflow/hooks/types/step/__init__.py
werkflow/hooks/types/step/decorator.py
werkflow/hooks/types/step/hook.py
werkflow/hooks/types/step/validator.py
werkflow/logging/__init__.py
werkflow/logging/logging_manager.py
werkflow/logging/werkflow_logger.py
werkflow/logging/config/__init__.py
werkflow/logging/config/logging_config.py
werkflow/logging/logger_types/__init__.py
werkflow/logging/logger_types/async_filesystem_logger.py
werkflow/logging/logger_types/async_logger.py
werkflow/logging/logger_types/async_spinner.py
werkflow/logging/logger_types/logger.py
werkflow/logging/logger_types/logger_types.py
werkflow/logging/logger_types/logger_types_map.py
werkflow/logging/logger_types/sync_filesystem_logger.py
werkflow/logging/logger_types/sync_logger.py
werkflow-0.3.0.dist-info/licenses/LICENSE
werkflow-0.3.0.dist-info/METADATA
werkflow-0.3.0.dist-info/WHEEL
werkflow-0.3.0.dist-info/entry_points.txt
werkflow-0.3.0.dist-info/top_level.txt
werkflow-0.3.0.dist-info/RECORD
