Metadata-Version: 2.4
Name: werkflow
Version: 0.3.0
Summary: Composable workflows for all.
Author-email: Ada Lundhe <adalundhe@lundhe.audio>
Project-URL: Homepage, https://github.com/adalundhe/werkflow
Keywords: pypi,cicd,python,werkflow,workflow
Classifier: Programming Language :: Python :: 3.11
Classifier: Programming Language :: Python :: 3.12
Classifier: Programming Language :: Python :: 3.13
Classifier: Operating System :: OS Independent
Requires-Python: >=3.11
License-File: LICENSE
Requires-Dist: click
Requires-Dist: pydantic
Requires-Dist: networkx
Requires-Dist: aiologger
Requires-Dist: yaspin
Requires-Dist: art
Requires-Dist: python-dotenv
Requires-Dist: werkflow-core
Provides-Extra: all
Requires-Dist: werkflow-aws; extra == "all"
Requires-Dist: werkflow-docker; extra == "all"
Requires-Dist: werkflow-encryption; extra == "all"
Requires-Dist: werkflow-file; extra == "all"
Requires-Dist: werkflow-git; extra == "all"
Requires-Dist: werkflow-github; extra == "all"
Requires-Dist: werkflow-http; extra == "all"
Requires-Dist: werkflow-metrik; extra == "all"
Requires-Dist: werkflow-python; extra == "all"
Requires-Dist: werkflow-secrets; extra == "all"
Requires-Dist: werkflow-shell; extra == "all"
Requires-Dist: werkflow-system; extra == "all"
Provides-Extra: aws
Requires-Dist: werkflow-aws; extra == "aws"
Provides-Extra: docker
Requires-Dist: werkflow-docker; extra == "docker"
Provides-Extra: encryption
Requires-Dist: werkflow-encryption; extra == "encryption"
Provides-Extra: file
Requires-Dist: werkflow-file; extra == "file"
Provides-Extra: git
Requires-Dist: werkflow-git; extra == "git"
Provides-Extra: github
Requires-Dist: werkflow-github; extra == "github"
Provides-Extra: http
Requires-Dist: werkflow-http; extra == "http"
Provides-Extra: metrikflow
Requires-Dist: werkflow-metrikflow; extra == "metrikflow"
Provides-Extra: python
Requires-Dist: werkflow-python; extra == "python"
Provides-Extra: secrets
Requires-Dist: werkflow-secrets; extra == "secrets"
Provides-Extra: shell
Requires-Dist: werkflow-shell; extra == "shell"
Provides-Extra: system
Requires-Dist: werkflow-system; extra == "system"
Dynamic: license-file
